composio_pydanticai/__init__.py
composio_pydanticai/toolset.py
composio_pydanticai-0.7.20.dist-info/METADATA
composio_pydanticai-0.7.20.dist-info/WHEEL
composio_pydanticai-0.7.20.dist-info/top_level.txt
composio_pydanticai-0.7.20.dist-info/RECORD
