Metadata-Version: 2.4
Name: composio_pydanticai
Version: 0.7.20
Summary: Use Composio to get array of strongly typed tools for Pydantic AI
Home-page: https://github.com/ComposioHQ/composio
Author: Siddharth
Author-email: tech@composio.dev
Classifier: Programming Language :: Python :: 3
Classifier: License :: OSI Approved :: Apache Software License
Classifier: Operating System :: OS Independent
Requires-Python: >=3.9,<4
Requires-Dist: composio_core<0.8.0,>=0.7.0
Requires-Dist: pydantic-ai>=0.0.36
Dynamic: author
Dynamic: author-email
Dynamic: classifier
Dynamic: description
Dynamic: description-content-type
Dynamic: home-page
Dynamic: requires-dist
Dynamic: requires-python
Dynamic: summary
